{
    "earlystopping": {
        "confusion_matrices": {
            "abs": [
                "[[1164, 73, 79, 1, 55], [44, 193, 130, 0, 45], [15, 27, 3601, 140, 162], [0, 0, 121, 784, 0], [6, 24, 64, 0, 1215]]"
            ]
        },
        "markov_matrices": {
            "abs": {
                "actual": [
                    "[[1122, 217, 18, 0, 15], [56, 131, 215, 0, 10], [138, 60, 3629, 84, 34], [13, 1, 70, 821, 0], [42, 3, 13, 0, 1250]]"
                ],
                "predicted": [
                    "[[1041, 149, 20, 0, 19], [22, 129, 144, 0, 22], [107, 26, 3728, 76, 57], [7, 1, 65, 849, 3], [51, 12, 38, 0, 1376]]"
                ]
            }
        },
        "metrics": {
            "downstream": {
                "cohen_kappa": [
                    0.8167728905973058
                ],
                "f1_scores": {
                    "N1": [
                        0.5294924554183814
                    ],
                    "N2": [
                        0.9070528967254408
                    ],
                    "N3": [
                        0.8568306010928962
                    ],
                    "REM": [
                        0.8722182340272794
                    ],
                    "Wake": [
                        0.8950403690888121
                    ],
                    "macro": [
                        0.8121269112705619
                    ]
                },
                "loss": [
                    0.3727348744869232
                ],
                "precisions": {
                    "N1": [
                        0.6088328075709779
                    ],
                    "N2": [
                        0.9013767209011264
                    ],
                    "N3": [
                        0.8475675675675676
                    ],
                    "REM": [
                        0.8226134055517942
                    ],
                    "Wake": [
                        0.9471114727420668
                    ],
                    "macro": [
                        0.8255003948667066
                    ]
                },
                "recalls": {
                    "N1": [
                        0.4684466019417476
                    ],
                    "N2": [
                        0.9128010139416983
                    ],
                    "N3": [
                        0.8662983425414365
                    ],
                    "REM": [
                        0.9281894576012223
                    ],
                    "Wake": [
                        0.8483965014577259
                    ],
                    "macro": [
                        0.8048263834967662
                    ]
                }
            }
        }
    },
    "test": {
        "confusion_matrices": {
            "abs": [
                "[[2276, 140, 183, 15, 142], [125, 297, 200, 21, 138], [102, 104, 5572, 615, 712], [1, 0, 125, 1355, 33], [30, 29, 275, 0, 1884]]"
            ]
        },
        "markov_matrices": {
            "abs": {
                "actual": [
                    "[[2267, 413, 59, 2, 15], [177, 247, 342, 0, 14], [239, 108, 6570, 128, 60], [22, 0, 108, 1384, 0], [50, 13, 26, 0, 2129]]"
                ],
                "predicted": [
                    "[[2074, 303, 91, 9, 57], [111, 189, 229, 3, 38], [216, 57, 5799, 89, 193], [27, 2, 69, 1896, 12], [105, 19, 167, 9, 2609]]"
                ]
            }
        },
        "metrics": {
            "downstream": {
                "cohen_kappa": [
                    0.7026579518719613
                ],
                "f1_scores": {
                    "N1": [
                        0.4396743153219837
                    ],
                    "N2": [
                        0.8279346210995542
                    ],
                    "N3": [
                        0.7698863636363638
                    ],
                    "REM": [
                        0.7349327091866588
                    ],
                    "Wake": [
                        0.860491493383743
                    ],
                    "macro": [
                        0.7265839005256607
                    ]
                },
                "loss": [
                    0.6801563789104593
                ],
                "precisions": {
                    "N1": [
                        0.5210526315789473
                    ],
                    "N2": [
                        0.8767899291896145
                    ],
                    "N3": [
                        0.6754735792622134
                    ],
                    "REM": [
                        0.6476452389137161
                    ],
                    "Wake": [
                        0.8981846882399369
                    ],
                    "macro": [
                        0.7238292134368857
                    ]
                },
                "recalls": {
                    "N1": [
                        0.38028169014084506
                    ],
                    "N2": [
                        0.7842364532019704
                    ],
                    "N3": [
                        0.8949801849405549
                    ],
                    "REM": [
                        0.8494138863841298
                    ],
                    "Wake": [
                        0.8258345428156749
                    ],
                    "macro": [
                        0.746949351496635
                    ]
                }
            }
        }
    },
    "train": {},
    "valid_pretraining": {}
}
