{
    "earlystopping": {
        "confusion_matrices": {
            "abs": [
                "[[1097, 134, 107, 15, 105], [40, 160, 146, 8, 54], [35, 111, 3118, 323, 115], [0, 3, 212, 835, 0], [28, 49, 132, 0, 856]]"
            ]
        },
        "markov_matrices": {
            "abs": {
                "actual": [
                    "[[1259, 184, 13, 0, 1], [48, 150, 197, 0, 13], [112, 70, 3412, 84, 24], [12, 1, 71, 966, 0], [26, 3, 9, 0, 1027]]"
                ],
                "predicted": [
                    "[[1000, 134, 49, 3, 13], [39, 222, 161, 2, 33], [108, 66, 3349, 113, 79], [16, 4, 97, 1061, 3], [36, 31, 59, 2, 1002]]"
                ]
            }
        },
        "metrics": {
            "downstream": {
                "cohen_kappa": [
                    0.6962194324956402
                ],
                "f1_scores": {
                    "N1": [
                        0.3699421965317919
                    ],
                    "N2": [
                        0.8407712012943239
                    ],
                    "N3": [
                        0.7485432541461228
                    ],
                    "REM": [
                        0.7799544419134398
                    ],
                    "Wake": [
                        0.8254326561324306
                    ],
                    "macro": [
                        0.7129287500036218
                    ]
                },
                "loss": [
                    0.9907861948013306
                ],
                "precisions": {
                    "N1": [
                        0.350109409190372
                    ],
                    "N2": [
                        0.839300134589502
                    ],
                    "N3": [
                        0.7070279424216765
                    ],
                    "REM": [
                        0.7575221238938054
                    ],
                    "Wake": [
                        0.9141666666666667
                    ],
                    "macro": [
                        0.7136252553524045
                    ]
                },
                "recalls": {
                    "N1": [
                        0.39215686274509803
                    ],
                    "N2": [
                        0.842247433819557
                    ],
                    "N3": [
                        0.7952380952380952
                    ],
                    "REM": [
                        0.8037558685446009
                    ],
                    "Wake": [
                        0.752400548696845
                    ],
                    "macro": [
                        0.7171597618088392
                    ]
                }
            }
        }
    },
    "test": {
        "confusion_matrices": {
            "abs": [
                "[[1384, 178, 194, 34, 219], [43, 196, 239, 7, 99], [43, 105, 5594, 376, 524], [0, 0, 210, 1648, 2], [41, 61, 437, 26, 1605]]"
            ]
        },
        "markov_matrices": {
            "abs": {
                "actual": [
                    "[[1680, 283, 29, 0, 17], [67, 196, 302, 0, 18], [192, 88, 6163, 147, 52], [23, 1, 123, 1713, 0], [46, 16, 25, 0, 2083]]"
                ],
                "predicted": [
                    "[[1237, 161, 60, 6, 47], [35, 242, 226, 0, 37], [129, 94, 6038, 173, 239], [20, 9, 150, 1904, 8], [89, 34, 200, 8, 2118]]"
                ]
            }
        },
        "metrics": {
            "downstream": {
                "cohen_kappa": [
                    0.6838509526040334
                ],
                "f1_scores": {
                    "N1": [
                        0.34875444839857656
                    ],
                    "N2": [
                        0.8401922499249024
                    ],
                    "N3": [
                        0.8342191850164515
                    ],
                    "REM": [
                        0.6949556180991556
                    ],
                    "Wake": [
                        0.7863636363636364
                    ],
                    "macro": [
                        0.7008970275605445
                    ]
                },
                "loss": [
                    1.1174226173987756
                ],
                "precisions": {
                    "N1": [
                        0.362962962962963
                    ],
                    "N2": [
                        0.8381780041953851
                    ],
                    "N3": [
                        0.7881396461023433
                    ],
                    "REM": [
                        0.6553695385871784
                    ],
                    "Wake": [
                        0.9159497021839841
                    ],
                    "macro": [
                        0.7121199708063708
                    ]
                },
                "recalls": {
                    "N1": [
                        0.3356164383561644
                    ],
                    "N2": [
                        0.8422161999397771
                    ],
                    "N3": [
                        0.886021505376344
                    ],
                    "REM": [
                        0.7396313364055299
                    ],
                    "Wake": [
                        0.6888999502239921
                    ],
                    "macro": [
                        0.6984770860603615
                    ]
                }
            }
        }
    },
    "train": {},
    "valid_pretraining": {}
}
