{
    "earlystopping": {
        "confusion_matrices": {
            "abs": [
                "[[1213, 193, 40, 1, 11], [42, 270, 79, 1, 16], [21, 422, 3005, 210, 44], [0, 106, 170, 774, 0], [8, 110, 27, 0, 920]]"
            ]
        },
        "markov_matrices": {
            "abs": {
                "actual": [
                    "[[1259, 184, 13, 0, 1], [48, 150, 197, 0, 13], [112, 70, 3412, 84, 24], [12, 1, 71, 966, 0], [26, 3, 9, 0, 1027]]"
                ],
                "predicted": [
                    "[[1081, 189, 4, 0, 9], [94, 789, 190, 0, 28], [75, 91, 3064, 63, 28], [8, 0, 55, 923, 0], [25, 32, 8, 0, 926]]"
                ]
            }
        },
        "metrics": {
            "downstream": {
                "cohen_kappa": [
                    0.7275142577815986
                ],
                "f1_scores": {
                    "N1": [
                        0.35785288270377735
                    ],
                    "N2": [
                        0.8557596468745551
                    ],
                    "N3": [
                        0.7603143418467584
                    ],
                    "REM": [
                        0.8949416342412452
                    ],
                    "Wake": [
                        0.8847556528081693
                    ],
                    "macro": [
                        0.7507248316949011
                    ]
                },
                "loss": [
                    0.5095299482345581
                ],
                "precisions": {
                    "N1": [
                        0.2452316076294278
                    ],
                    "N2": [
                        0.9048479373682625
                    ],
                    "N3": [
                        0.7849898580121704
                    ],
                    "REM": [
                        0.9283551967709385
                    ],
                    "Wake": [
                        0.9447040498442367
                    ],
                    "macro": [
                        0.7616257299250072
                    ]
                },
                "recalls": {
                    "N1": [
                        0.6617647058823529
                    ],
                    "N2": [
                        0.81172339276067
                    ],
                    "N3": [
                        0.7371428571428571
                    ],
                    "REM": [
                        0.863849765258216
                    ],
                    "Wake": [
                        0.8319615912208504
                    ],
                    "macro": [
                        0.7812884624529893
                    ]
                }
            }
        }
    },
    "test": {
        "confusion_matrices": {
            "abs": [
                "[[1410, 350, 139, 4, 106], [31, 369, 133, 4, 47], [26, 364, 5518, 306, 428], [0, 0, 429, 1427, 4], [16, 325, 209, 0, 1620]]"
            ]
        },
        "markov_matrices": {
            "abs": {
                "actual": [
                    "[[1680, 283, 29, 0, 17], [67, 196, 302, 0, 18], [192, 88, 6163, 147, 52], [23, 1, 123, 1713, 0], [46, 16, 25, 0, 2083]]"
                ],
                "predicted": [
                    "[[1174, 280, 21, 0, 8], [114, 911, 310, 0, 73], [144, 137, 5951, 91, 104], [10, 1, 79, 1650, 1], [40, 79, 67, 0, 2019]]"
                ]
            }
        },
        "metrics": {
            "downstream": {
                "cohen_kappa": [
                    0.6809384446996032
                ],
                "f1_scores": {
                    "N1": [
                        0.3704819277108434
                    ],
                    "N2": [
                        0.8443764345830146
                    ],
                    "N3": [
                        0.7925576228825326
                    ],
                    "REM": [
                        0.7405714285714285
                    ],
                    "Wake": [
                        0.8075601374570447
                    ],
                    "macro": [
                        0.7111095102409728
                    ]
                },
                "loss": [
                    0.6464636142437274
                ],
                "precisions": {
                    "N1": [
                        0.26207386363636365
                    ],
                    "N2": [
                        0.858431860609832
                    ],
                    "N3": [
                        0.8196438828259621
                    ],
                    "REM": [
                        0.7346938775510204
                    ],
                    "Wake": [
                        0.9507754551584626
                    ],
                    "macro": [
                        0.7251237879563281
                    ]
                },
                "recalls": {
                    "N1": [
                        0.6318493150684932
                    ],
                    "N2": [
                        0.8307738632941885
                    ],
                    "N3": [
                        0.7672043010752688
                    ],
                    "REM": [
                        0.7465437788018433
                    ],
                    "Wake": [
                        0.701841712294674
                    ],
                    "macro": [
                        0.7356425941068936
                    ]
                }
            }
        }
    },
    "train": {},
    "valid_pretraining": {}
}
