{
    "earlystopping": {
        "confusion_matrices": {
            "abs": [
                "[[1145, 138, 73, 2, 14], [11, 243, 142, 0, 16], [17, 52, 3589, 236, 51], [0, 0, 53, 851, 1], [5, 45, 61, 0, 1198]]"
            ]
        },
        "markov_matrices": {
            "abs": {
                "actual": [
                    "[[1122, 217, 18, 0, 15], [56, 131, 215, 0, 10], [138, 60, 3629, 84, 34], [13, 1, 70, 821, 0], [42, 3, 13, 0, 1250]]"
                ],
                "predicted": [
                    "[[984, 182, 11, 0, 1], [59, 233, 169, 0, 17], [98, 42, 3671, 51, 56], [12, 3, 36, 1038, 0], [24, 18, 31, 0, 1206]]"
                ]
            }
        },
        "metrics": {
            "downstream": {
                "cohen_kappa": [
                    0.8312408964840602
                ],
                "f1_scores": {
                    "N1": [
                        0.5460674157303371
                    ],
                    "N2": [
                        0.9128831234897622
                    ],
                    "N3": [
                        0.8535606820461383
                    ],
                    "REM": [
                        0.925453843182696
                    ],
                    "Wake": [
                        0.8980392156862745
                    ],
                    "macro": [
                        0.8272008560270416
                    ]
                },
                "loss": [
                    0.33979710936546326
                ],
                "precisions": {
                    "N1": [
                        0.5083682008368201
                    ],
                    "N2": [
                        0.9160285860132721
                    ],
                    "N3": [
                        0.7814508723599632
                    ],
                    "REM": [
                        0.9359375
                    ],
                    "Wake": [
                        0.9719864176570459
                    ],
                    "macro": [
                        0.8227543153734203
                    ]
                },
                "recalls": {
                    "N1": [
                        0.5898058252427184
                    ],
                    "N2": [
                        0.9097591888466413
                    ],
                    "N3": [
                        0.9403314917127071
                    ],
                    "REM": [
                        0.9152024446142093
                    ],
                    "Wake": [
                        0.8345481049562682
                    ],
                    "macro": [
                        0.8379294110745089
                    ]
                }
            }
        }
    },
    "test": {
        "confusion_matrices": {
            "abs": [
                "[[2073, 339, 159, 8, 177], [30, 429, 186, 3, 133], [34, 207, 5476, 383, 1005], [2, 0, 96, 1354, 62], [7, 53, 119, 0, 2039]]"
            ]
        },
        "markov_matrices": {
            "abs": {
                "actual": [
                    "[[2267, 413, 59, 2, 15], [177, 247, 342, 0, 14], [239, 108, 6570, 128, 60], [22, 0, 108, 1384, 0], [50, 13, 26, 0, 2129]]"
                ],
                "predicted": [
                    "[[1779, 330, 17, 0, 19], [143, 523, 313, 1, 48], [152, 123, 5588, 55, 118], [15, 1, 44, 1684, 4], [56, 51, 74, 8, 3227]]"
                ]
            }
        },
        "metrics": {
            "downstream": {
                "cohen_kappa": [
                    0.7059309976887937
                ],
                "f1_scores": {
                    "N1": [
                        0.4742951907131012
                    ],
                    "N2": [
                        0.8334221139943688
                    ],
                    "N3": [
                        0.8301655426118946
                    ],
                    "REM": [
                        0.723819666311679
                    ],
                    "Wake": [
                        0.8457772337821297
                    ],
                    "macro": [
                        0.7414959494826346
                    ]
                },
                "loss": [
                    0.7916742522141029
                ],
                "precisions": {
                    "N1": [
                        0.4173151750972763
                    ],
                    "N2": [
                        0.9072233267064281
                    ],
                    "N3": [
                        0.7745995423340961
                    ],
                    "REM": [
                        0.5968969555035128
                    ],
                    "Wake": [
                        0.9659832246039143
                    ],
                    "macro": [
                        0.7324036448490455
                    ]
                },
                "recalls": {
                    "N1": [
                        0.5492957746478874
                    ],
                    "N2": [
                        0.7707248416608022
                    ],
                    "N3": [
                        0.8943196829590488
                    ],
                    "REM": [
                        0.9192966636609559
                    ],
                    "Wake": [
                        0.752177068214804
                    ],
                    "macro": [
                        0.7771628062286997
                    ]
                }
            }
        }
    },
    "train": {},
    "valid_ssl": {}
}
