{
    "earlystopping": {
        "confusion_matrices": {
            "abs": [
                "[[1244, 94, 114, 0, 34], [63, 166, 196, 0, 36], [55, 88, 3413, 62, 210], [47, 19, 231, 650, 79], [17, 65, 199, 0, 926]]"
            ]
        },
        "markov_matrices": {
            "abs": {
                "actual": [
                    "[[1212, 234, 24, 0, 15], [70, 143, 236, 0, 12], [144, 80, 3479, 94, 31], [13, 1, 80, 932, 0], [46, 3, 9, 0, 1149]]"
                ],
                "predicted": [
                    "[[1177, 161, 64, 1, 22], [53, 168, 193, 1, 17], [143, 86, 3781, 47, 96], [10, 0, 33, 644, 25], [42, 17, 82, 19, 1125]]"
                ]
            }
        },
        "metrics": {
            "downstream": {
                "cohen_kappa": [
                    0.7046832521653053
                ],
                "f1_scores": {
                    "N1": [
                        0.3717805151175812
                    ],
                    "N2": [
                        0.8552812930710437
                    ],
                    "N3": [
                        0.7479861910241657
                    ],
                    "REM": [
                        0.7431781701444623
                    ],
                    "Wake": [
                        0.8543956043956044
                    ],
                    "macro": [
                        0.7145243547505715
                    ]
                },
                "loss": [
                    0.6733050346374512
                ],
                "precisions": {
                    "N1": [
                        0.38425925925925924
                    ],
                    "N2": [
                        0.8218155550204671
                    ],
                    "N3": [
                        0.9129213483146067
                    ],
                    "REM": [
                        0.7206225680933852
                    ],
                    "Wake": [
                        0.8723702664796634
                    ],
                    "macro": [
                        0.7423977994334764
                    ]
                },
                "recalls": {
                    "N1": [
                        0.3600867678958785
                    ],
                    "N2": [
                        0.8915882967607106
                    ],
                    "N3": [
                        0.6335282651072125
                    ],
                    "REM": [
                        0.7671913835956918
                    ],
                    "Wake": [
                        0.8371467025572006
                    ],
                    "macro": [
                        0.6979082831833388
                    ]
                }
            }
        }
    },
    "test": {
        "confusion_matrices": {
            "abs": [
                "[[1432, 129, 105, 18, 529], [197, 285, 170, 1, 181], [361, 108, 5410, 203, 516], [104, 0, 446, 956, 9], [38, 16, 265, 0, 2330]]"
            ]
        },
        "markov_matrices": {
            "abs": {
                "actual": [
                    "[[1846, 336, 22, 0, 8], [106, 332, 383, 0, 13], [188, 148, 6049, 144, 69], [24, 1, 119, 1371, 0], [48, 17, 25, 0, 2559]]"
                ],
                "predicted": [
                    "[[1707, 242, 100, 22, 60], [83, 190, 221, 0, 44], [211, 78, 5855, 85, 167], [43, 0, 61, 1061, 13], [88, 27, 159, 10, 3281]]"
                ]
            }
        },
        "metrics": {
            "downstream": {
                "cohen_kappa": [
                    0.644980900128251
                ],
                "f1_scores": {
                    "N1": [
                        0.41545189504373176
                    ],
                    "N2": [
                        0.8326920116977067
                    ],
                    "N3": [
                        0.7099888600074267
                    ],
                    "REM": [
                        0.7499195365304152
                    ],
                    "Wake": [
                        0.6591484464902186
                    ],
                    "macro": [
                        0.6734401499538999
                    ]
                },
                "loss": [
                    1.284952234338831
                ],
                "precisions": {
                    "N1": [
                        0.5297397769516728
                    ],
                    "N2": [
                        0.8458411507191995
                    ],
                    "N3": [
                        0.8115449915110357
                    ],
                    "REM": [
                        0.6535764375876578
                    ],
                    "Wake": [
                        0.6716697936210131
                    ],
                    "macro": [
                        0.7024744300781157
                    ]
                },
                "recalls": {
                    "N1": [
                        0.34172661870503596
                    ],
                    "N2": [
                        0.8199454380115186
                    ],
                    "N3": [
                        0.6310231023102311
                    ],
                    "REM": [
                        0.8795771989429974
                    ],
                    "Wake": [
                        0.6470854044283778
                    ],
                    "macro": [
                        0.6638715524796321
                    ]
                }
            }
        }
    },
    "train": {},
    "valid_pretraining": {}
}
