{
    "earlystopping": {
        "confusion_matrices": {
            "abs": [
                "[[1286, 80, 74, 9, 9], [68, 157, 146, 0, 37], [62, 51, 3365, 138, 86], [3, 0, 341, 706, 0], [18, 62, 123, 0, 862]]"
            ]
        },
        "markov_matrices": {
            "abs": {
                "actual": [
                    "[[1259, 184, 13, 0, 1], [48, 150, 197, 0, 13], [112, 70, 3412, 84, 24], [12, 1, 71, 966, 0], [26, 3, 9, 0, 1027]]"
                ],
                "predicted": [
                    "[[1210, 140, 64, 4, 18], [37, 154, 134, 0, 25], [148, 35, 3746, 69, 51], [10, 1, 62, 779, 1], [31, 20, 43, 1, 899]]"
                ]
            }
        },
        "metrics": {
            "downstream": {
                "cohen_kappa": [
                    0.7479933249487382
                ],
                "f1_scores": {
                    "N1": [
                        0.41424802110817943
                    ],
                    "N2": [
                        0.8682750612824152
                    ],
                    "N3": [
                        0.7419863373620599
                    ],
                    "REM": [
                        0.8372996600291404
                    ],
                    "Wake": [
                        0.8884283246977548
                    ],
                    "macro": [
                        0.7500474808959099
                    ]
                },
                "loss": [
                    0.587041974067688
                ],
                "precisions": {
                    "N1": [
                        0.44857142857142857
                    ],
                    "N2": [
                        0.8310693998518153
                    ],
                    "N3": [
                        0.8276670574443142
                    ],
                    "REM": [
                        0.8672032193158954
                    ],
                    "Wake": [
                        0.894919972164231
                    ],
                    "macro": [
                        0.7738862154695368
                    ]
                },
                "recalls": {
                    "N1": [
                        0.38480392156862747
                    ],
                    "N2": [
                        0.9089681253376554
                    ],
                    "N3": [
                        0.6723809523809524
                    ],
                    "REM": [
                        0.8093896713615023
                    ],
                    "Wake": [
                        0.8820301783264746
                    ],
                    "macro": [
                        0.7315145697950424
                    ]
                }
            }
        }
    },
    "test": {
        "confusion_matrices": {
            "abs": [
                "[[1520, 63, 211, 1, 214], [91, 203, 216, 3, 71], [133, 53, 5860, 318, 278], [5, 0, 355, 1498, 2], [135, 209, 331, 20, 1475]]"
            ]
        },
        "markov_matrices": {
            "abs": {
                "actual": [
                    "[[1680, 283, 29, 0, 17], [67, 196, 302, 0, 18], [192, 88, 6163, 147, 52], [23, 1, 123, 1713, 0], [46, 16, 25, 0, 2083]]"
                ],
                "predicted": [
                    "[[1441, 225, 143, 7, 68], [67, 226, 187, 0, 48], [271, 38, 6386, 135, 142], [20, 0, 120, 1692, 8], [84, 39, 137, 6, 1774]]"
                ]
            }
        },
        "metrics": {
            "downstream": {
                "cohen_kappa": [
                    0.6946987805779139
                ],
                "f1_scores": {
                    "N1": [
                        0.36510791366906475
                    ],
                    "N2": [
                        0.8608152772677194
                    ],
                    "N3": [
                        0.8097297297297297
                    ],
                    "REM": [
                        0.7007125890736342
                    ],
                    "Wake": [
                        0.7808887747238633
                    ],
                    "macro": [
                        0.7034508568928023
                    ]
                },
                "loss": [
                    0.81188598045936
                ],
                "precisions": {
                    "N1": [
                        0.38446969696969696
                    ],
                    "N2": [
                        0.840384339595583
                    ],
                    "N3": [
                        0.8141304347826087
                    ],
                    "REM": [
                        0.7230392156862745
                    ],
                    "Wake": [
                        0.8067940552016986
                    ],
                    "macro": [
                        0.7137635484471724
                    ]
                },
                "recalls": {
                    "N1": [
                        0.3476027397260274
                    ],
                    "N2": [
                        0.8822643781993376
                    ],
                    "N3": [
                        0.8053763440860215
                    ],
                    "REM": [
                        0.6797235023041475
                    ],
                    "Wake": [
                        0.7565953210552514
                    ],
                    "macro": [
                        0.694312457074157
                    ]
                }
            }
        }
    },
    "train": {},
    "valid_pretraining": {}
}
