{
    "earlystopping": {
        "confusion_matrices": {
            "abs": [
                "[[1188, 60, 146, 5, 59], [30, 107, 221, 0, 50], [21, 13, 3446, 147, 75], [1, 0, 245, 804, 0], [9, 1, 227, 0, 828]]"
            ]
        },
        "markov_matrices": {
            "abs": {
                "actual": [
                    "[[1259, 184, 13, 0, 1], [48, 150, 197, 0, 13], [112, 70, 3412, 84, 24], [12, 1, 71, 966, 0], [26, 3, 9, 0, 1027]]"
                ],
                "predicted": [
                    "[[1065, 102, 73, 0, 8], [25, 69, 77, 0, 10], [123, 7, 4045, 53, 57], [11, 1, 39, 903, 2], [24, 2, 51, 0, 935]]"
                ]
            }
        },
        "metrics": {
            "downstream": {
                "cohen_kappa": [
                    0.7431742810964387
                ],
                "f1_scores": {
                    "N1": [
                        0.3633276740237691
                    ],
                    "N2": [
                        0.8629022161011642
                    ],
                    "N3": [
                        0.8015952143569292
                    ],
                    "REM": [
                        0.797303803562831
                    ],
                    "Wake": [
                        0.8777244181751016
                    ],
                    "macro": [
                        0.7405706652439589
                    ]
                },
                "loss": [
                    0.7685815691947937
                ],
                "precisions": {
                    "N1": [
                        0.5911602209944752
                    ],
                    "N2": [
                        0.8042007001166861
                    ],
                    "N3": [
                        0.8410041841004184
                    ],
                    "REM": [
                        0.8181818181818182
                    ],
                    "Wake": [
                        0.9511609287429944
                    ],
                    "macro": [
                        0.8011415704272784
                    ]
                },
                "recalls": {
                    "N1": [
                        0.2622549019607843
                    ],
                    "N2": [
                        0.930848190167477
                    ],
                    "N3": [
                        0.7657142857142857
                    ],
                    "REM": [
                        0.7774647887323943
                    ],
                    "Wake": [
                        0.8148148148148148
                    ],
                    "macro": [
                        0.7102193962779512
                    ]
                }
            }
        }
    },
    "test": {
        "confusion_matrices": {
            "abs": [
                "[[1404, 88, 471, 7, 39], [66, 106, 371, 3, 38], [58, 13, 6209, 221, 141], [2, 0, 343, 1515, 0], [35, 30, 942, 11, 1152]]"
            ]
        },
        "markov_matrices": {
            "abs": {
                "actual": [
                    "[[1680, 283, 29, 0, 17], [67, 196, 302, 0, 18], [192, 88, 6163, 147, 52], [23, 1, 123, 1713, 0], [46, 16, 25, 0, 2083]]"
                ],
                "predicted": [
                    "[[1262, 118, 168, 3, 14], [20, 98, 104, 0, 15], [244, 11, 7828, 105, 147], [15, 2, 88, 1647, 5], [23, 8, 148, 2, 1189]]"
                ]
            }
        },
        "metrics": {
            "downstream": {
                "cohen_kappa": [
                    0.656160579315039
                ],
                "f1_scores": {
                    "N1": [
                        0.2582216808769793
                    ],
                    "N2": [
                        0.8290826545600214
                    ],
                    "N3": [
                        0.8377108100635887
                    ],
                    "REM": [
                        0.6508474576271188
                    ],
                    "Wake": [
                        0.7856743144935646
                    ],
                    "macro": [
                        0.6723073835242545
                    ]
                },
                "loss": [
                    0.9854899186354417
                ],
                "precisions": {
                    "N1": [
                        0.4472573839662447
                    ],
                    "N2": [
                        0.744841650671785
                    ],
                    "N3": [
                        0.8622652248150257
                    ],
                    "REM": [
                        0.8408759124087591
                    ],
                    "Wake": [
                        0.8971246006389776
                    ],
                    "macro": [
                        0.7584729545001585
                    ]
                },
                "recalls": {
                    "N1": [
                        0.1815068493150685
                    ],
                    "N2": [
                        0.9348087925323698
                    ],
                    "N3": [
                        0.8145161290322581
                    ],
                    "REM": [
                        0.5308755760368664
                    ],
                    "Wake": [
                        0.6988551518168243
                    ],
                    "macro": [
                        0.6321124997466775
                    ]
                }
            }
        }
    },
    "train": {},
    "valid_pretraining": {}
}
