{
    "earlystopping": {
        "confusion_matrices": {
            "abs": [
                "[[247, 74, 426, 5, 356], [43, 33, 202, 2, 148], [465, 122, 1836, 257, 1417], [87, 19, 57, 362, 383], [200, 62, 452, 0, 539]]"
            ]
        },
        "markov_matrices": {
            "abs": {
                "actual": [
                    "[[862, 210, 21, 0, 14], [64, 148, 206, 0, 10], [130, 65, 3781, 89, 32], [11, 1, 77, 819, 0], [40, 4, 12, 0, 1197]]"
                ],
                "predicted": [
                    "[[594, 96, 143, 12, 196], [43, 107, 113, 3, 44], [180, 45, 2437, 49, 262], [14, 4, 45, 527, 36], [211, 58, 234, 35, 2305]]"
                ]
            }
        },
        "metrics": {
            "downstream": {
                "cohen_kappa": [
                    0.13711396029197265
                ],
                "f1_scores": {
                    "N1": [
                        0.08943089430894309
                    ],
                    "N2": [
                        0.5193776520509193
                    ],
                    "N3": [
                        0.4719687092568448
                    ],
                    "REM": [
                        0.26318359375
                    ],
                    "Wake": [
                        0.22976744186046513
                    ],
                    "macro": [
                        0.3147456582454345
                    ]
                },
                "loss": [
                    4.650991439819336
                ],
                "precisions": {
                    "N1": [
                        0.1064516129032258
                    ],
                    "N2": [
                        0.6175580221997982
                    ],
                    "N3": [
                        0.5782747603833865
                    ],
                    "REM": [
                        0.18958846289131198
                    ],
                    "Wake": [
                        0.23704414587332054
                    ],
                    "macro": [
                        0.34578340085020864
                    ]
                },
                "recalls": {
                    "N1": [
                        0.07710280373831775
                    ],
                    "N2": [
                        0.44813278008298757
                    ],
                    "N3": [
                        0.3986784140969163
                    ],
                    "REM": [
                        0.4301675977653631
                    ],
                    "Wake": [
                        0.22292418772563177
                    ],
                    "macro": [
                        0.3154011566818433
                    ]
                }
            }
        }
    },
    "test": {
        "confusion_matrices": {
            "abs": [
                "[[561, 123, 948, 43, 696], [141, 69, 318, 12, 214], [572, 117, 3978, 299, 1518], [73, 3, 302, 518, 545], [374, 89, 665, 3, 993]]"
            ]
        },
        "markov_matrices": {
            "abs": {
                "actual": [
                    "[[1925, 362, 71, 0, 13], [125, 270, 344, 1, 14], [256, 108, 5893, 174, 52], [18, 2, 155, 1266, 0], [46, 12, 21, 0, 2045]]"
                ],
                "predicted": [
                    "[[971, 150, 267, 26, 307], [49, 132, 166, 11, 43], [325, 55, 5305, 124, 401], [28, 8, 131, 685, 23], [347, 56, 342, 29, 3192]]"
                ]
            }
        },
        "metrics": {
            "downstream": {
                "cohen_kappa": [
                    0.2203762577900662
                ],
                "f1_scores": {
                    "N1": [
                        0.11948051948051948
                    ],
                    "N2": [
                        0.6267034265458842
                    ],
                    "N3": [
                        0.4473229706390328
                    ],
                    "REM": [
                        0.32610837438423645
                    ],
                    "Wake": [
                        0.27419354838709675
                    ],
                    "macro": [
                        0.3587617678873539
                    ]
                },
                "loss": [
                    4.037553347074068
                ],
                "precisions": {
                    "N1": [
                        0.17206982543640897
                    ],
                    "N2": [
                        0.6404765738206408
                    ],
                    "N3": [
                        0.592
                    ],
                    "REM": [
                        0.2503782148260212
                    ],
                    "Wake": [
                        0.32597327135386406
                    ],
                    "macro": [
                        0.39617957708738705
                    ]
                },
                "recalls": {
                    "N1": [
                        0.09151193633952255
                    ],
                    "N2": [
                        0.6135101789019124
                    ],
                    "N3": [
                        0.35947258848022207
                    ],
                    "REM": [
                        0.4675141242937853
                    ],
                    "Wake": [
                        0.2366090257275411
                    ],
                    "macro": [
                        0.35372357074859667
                    ]
                }
            }
        }
    },
    "train": {},
    "valid_ssl": {}
}
