{
    "earlystopping": {
        "confusion_matrices": {
            "abs": [
                "[[1109, 3, 293, 1, 82], [179, 10, 141, 0, 141], [307, 39, 2947, 114, 433], [83, 2, 283, 543, 8], [132, 0, 156, 0, 878]]"
            ]
        },
        "markov_matrices": {
            "abs": {
                "actual": [
                    "[[1224, 231, 17, 0, 15], [74, 164, 222, 0, 11], [132, 73, 3531, 73, 31], [11, 0, 62, 846, 0], [46, 3, 8, 0, 1109]]"
                ],
                "predicted": [
                    "[[1645, 9, 88, 0, 68], [2, 10, 34, 0, 8], [98, 25, 3408, 87, 202], [2, 0, 82, 566, 7], [62, 10, 208, 5, 1257]]"
                ]
            }
        },
        "metrics": {
            "downstream": {
                "cohen_kappa": [
                    0.5539493365491492
                ],
                "f1_scores": {
                    "N1": [
                        0.03809523809523809
                    ],
                    "N2": [
                        0.7694516971279374
                    ],
                    "N3": [
                        0.6886493341788206
                    ],
                    "REM": [
                        0.6484490398818317
                    ],
                    "Wake": [
                        0.6725288053365676
                    ],
                    "macro": [
                        0.5634348229240791
                    ]
                },
                "loss": [
                    3.304727554321289
                ],
                "precisions": {
                    "N1": [
                        0.18518518518518517
                    ],
                    "N2": [
                        0.7714659685863874
                    ],
                    "N3": [
                        0.8252279635258358
                    ],
                    "REM": [
                        0.569390402075227
                    ],
                    "Wake": [
                        0.612707182320442
                    ],
                    "macro": [
                        0.5927953403386155
                    ]
                },
                "recalls": {
                    "N1": [
                        0.021231422505307854
                    ],
                    "N2": [
                        0.7674479166666667
                    ],
                    "N3": [
                        0.5908596300326442
                    ],
                    "REM": [
                        0.7530017152658662
                    ],
                    "Wake": [
                        0.7452956989247311
                    ],
                    "macro": [
                        0.5755672766790433
                    ]
                }
            }
        }
    },
    "test": {
        "confusion_matrices": {
            "abs": [
                "[[1717, 17, 635, 4, 143], [213, 3, 306, 4, 180], [221, 19, 4964, 340, 987], [0, 1, 430, 1003, 93], [208, 2, 729, 16, 1216]]"
            ]
        },
        "markov_matrices": {
            "abs": {
                "actual": [
                    "[[2107, 335, 57, 1, 15], [101, 257, 328, 0, 20], [233, 100, 5972, 176, 50], [18, 3, 155, 1350, 1], [56, 11, 19, 0, 2085]]"
                ],
                "predicted": [
                    "[[2017, 6, 165, 0, 171], [1, 12, 24, 0, 5], [170, 20, 6412, 125, 337], [2, 0, 120, 1217, 27], [168, 4, 343, 25, 2079]]"
                ]
            }
        },
        "metrics": {
            "downstream": {
                "cohen_kappa": [
                    0.49465524142274253
                ],
                "f1_scores": {
                    "N1": [
                        0.008021390374331552
                    ],
                    "N2": [
                        0.7302684810592129
                    ],
                    "N3": [
                        0.6931582584657913
                    ],
                    "REM": [
                        0.5077244258872651
                    ],
                    "Wake": [
                        0.7044102564102565
                    ],
                    "macro": [
                        0.5287165624393715
                    ]
                },
                "loss": [
                    3.699217337149161
                ],
                "precisions": {
                    "N1": [
                        0.07142857142857142
                    ],
                    "N2": [
                        0.702718006795017
                    ],
                    "N3": [
                        0.733723482077542
                    ],
                    "REM": [
                        0.464299350897289
                    ],
                    "Wake": [
                        0.7278507842306062
                    ],
                    "macro": [
                        0.5400040390858052
                    ]
                },
                "recalls": {
                    "N1": [
                        0.00424929178470255
                    ],
                    "N2": [
                        0.7600673709998469
                    ],
                    "N3": [
                        0.6568434839554682
                    ],
                    "REM": [
                        0.5601105481345002
                    ],
                    "Wake": [
                        0.6824324324324325
                    ],
                    "macro": [
                        0.5327406254613901
                    ]
                }
            }
        }
    },
    "train": {},
    "valid_pretraining": {}
}
